install.json
jupyterlab_niivue/__init__.py
jupyterlab_niivue/_version.py
jupyterlab_niivue/handlers.py
jupyterlab_niivue/labextension/package.json
jupyterlab_niivue/labextension/schemas/@niivue/jupyter/package.json.orig
jupyterlab_niivue/labextension/static/467.aa910894667785d5b83f.js
jupyterlab_niivue/labextension/static/508.27ab2c9700e34ff4d1f7.js
jupyterlab_niivue/labextension/static/fb5df6f16a07d813e42a.png
jupyterlab_niivue/labextension/static/remoteEntry.090d5a2c306b8758af3a.js
jupyterlab_niivue/labextension/static/style.js
jupyterlab_niivue/labextension/static/third-party-licenses.json
jupyterlab_niivue/labextension/static/niivue/blosc-D1xNXZJs.js
jupyterlab_niivue/labextension/static/niivue/blosc-D1xNXZJs.js.map
jupyterlab_niivue/labextension/static/niivue/chunk-INHXZS53-DiyuLb3Z.js
jupyterlab_niivue/labextension/static/niivue/chunk-INHXZS53-DiyuLb3Z.js.map
jupyterlab_niivue/labextension/static/niivue/events.d.ts
jupyterlab_niivue/labextension/static/niivue/favicon.ico
jupyterlab_niivue/labextension/static/niivue/index.css
jupyterlab_niivue/labextension/static/niivue/index.d.ts
jupyterlab_niivue/labextension/static/niivue/index.js
jupyterlab_niivue/labextension/static/niivue/index.js.map
jupyterlab_niivue/labextension/static/niivue/lz4-1Ws5oVWR.js
jupyterlab_niivue/labextension/static/niivue/lz4-1Ws5oVWR.js.map
jupyterlab_niivue/labextension/static/niivue/main.d.ts
jupyterlab_niivue/labextension/static/niivue/niivue_icon.png
jupyterlab_niivue/labextension/static/niivue/niivue_icon_transparent_contrast.png
jupyterlab_niivue/labextension/static/niivue/readyState.d.ts
jupyterlab_niivue/labextension/static/niivue/settings.d.ts
jupyterlab_niivue/labextension/static/niivue/test-setup.d.ts
jupyterlab_niivue/labextension/static/niivue/types.d.ts
jupyterlab_niivue/labextension/static/niivue/utility.d.ts
jupyterlab_niivue/labextension/static/niivue/zstd-C4EcZnjq.js
jupyterlab_niivue/labextension/static/niivue/zstd-C4EcZnjq.js.map
jupyterlab_niivue-0.2.3.dist-info/METADATA
jupyterlab_niivue-0.2.3.dist-info/WHEEL
jupyterlab_niivue-0.2.3.dist-info/licenses/LICENSE
jupyterlab_niivue-0.2.3.dist-info/RECORD
