Metadata-Version: 2.4
Name: jupyterlab_niivue
Version: 0.2.3
Dynamic: Keywords
Summary: A JupyterLab extension for viewing NIfTI files with Niivue
Project-URL: Homepage, https://github.com/niivue/niivue-vscode/tree/main/apps/jupyter
Project-URL: Bug Tracker, https://github.com/niivue/niivue-vscode/issues
Project-URL: Repository, https://github.com/niivue/niivue-vscode.git
Author-email: Korbinian Eckstein <korbinian90@gmail.com>
License: BSD 2-Clause License
License-File: LICENSE
Classifier: Framework :: Jupyter
Classifier: Framework :: Jupyter :: JupyterLab
Classifier: Framework :: Jupyter :: JupyterLab :: 4
Classifier: Framework :: Jupyter :: JupyterLab :: Extensions
Classifier: Framework :: Jupyter :: JupyterLab :: Extensions :: Prebuilt
Classifier: License :: OSI Approved :: BSD License
Classifier: Programming Language :: Python
Classifier: Programming Language :: Python :: 3
Classifier: Programming Language :: Python :: 3.8
Classifier: Programming Language :: Python :: 3.9
Classifier: Programming Language :: Python :: 3.10
Classifier: Programming Language :: Python :: 3.11
Classifier: Programming Language :: Python :: 3.12
Requires-Python: >=3.8
Provides-Extra: test
Requires-Dist: coverage; extra == 'test'
Requires-Dist: pytest; extra == 'test'
Requires-Dist: pytest-asyncio; extra == 'test'
Requires-Dist: pytest-cov; extra == 'test'
Requires-Dist: pytest-jupyter[server]>=0.4.0; extra == 'test'
Requires-Dist: pytest-xvfb; extra == 'test'
